styxsingularity/__init__.py
styxsingularity-0.6.0.dist-info/WHEEL
styxsingularity-0.6.0.dist-info/METADATA
styxsingularity-0.6.0.dist-info/RECORD
