Metadata-Version: 2.4
Name: styxsingularity
Version: 0.6.0
Summary: Singularity/Apptainer integration for Styx compiled wrappers
Author: Florian Rupprecht
Author-email: Florian Rupprecht <33600480+nx10@users.noreply.github.com>
License-Expression: MIT
Requires-Dist: styxdefs>=0.5.0,<0.6
Requires-Python: >=3.10
